passagemath_repl/__init__.py
passagemath_repl-10.6.43.data/data/share/jupyter/kernels/sagemath/kernel.json
passagemath_repl-10.6.43.data/data/share/jupyter/kernels/sagemath/logo-64x64.png
passagemath_repl-10.6.43.data/data/share/jupyter/kernels/sagemath/logo.svg
passagemath_repl-10.6.43.data/scripts/sage-cachegrind
passagemath_repl-10.6.43.data/scripts/sage-callgrind
passagemath_repl-10.6.43.data/scripts/sage-cleaner
passagemath_repl-10.6.43.data/scripts/sage-coverage
passagemath_repl-10.6.43.data/scripts/sage-eval
passagemath_repl-10.6.43.data/scripts/sage-fixdoctests
passagemath_repl-10.6.43.data/scripts/sage-inline-fortran
passagemath_repl-10.6.43.data/scripts/sage-ipynb2rst
passagemath_repl-10.6.43.data/scripts/sage-ipython
passagemath_repl-10.6.43.data/scripts/sage-massif
passagemath_repl-10.6.43.data/scripts/sage-notebook
passagemath_repl-10.6.43.data/scripts/sage-omega
passagemath_repl-10.6.43.data/scripts/sage-preparse
passagemath_repl-10.6.43.data/scripts/sage-run
passagemath_repl-10.6.43.data/scripts/sage-run-cython
passagemath_repl-10.6.43.data/scripts/sage-runtests
passagemath_repl-10.6.43.data/scripts/sage-startuptime.py
passagemath_repl-10.6.43.data/scripts/sage-valgrind
sage/all__sagemath_repl.py
sage/doctest/__init__.py
sage/doctest/__main__.py
sage/doctest/all.py
sage/doctest/check_tolerance.py
sage/doctest/control.py
sage/doctest/external.py
sage/doctest/fixtures.py
sage/doctest/forker.py
sage/doctest/marked_output.py
sage/doctest/parsing.py
sage/doctest/parsing_test.py
sage/doctest/reporting.py
sage/doctest/rif_tol.py
sage/doctest/sources.py
sage/doctest/test.py
sage/doctest/util.py
sage/doctest/tests/1second.rst
sage/doctest/tests/99seconds.rst
sage/doctest/tests/abort.rst
sage/doctest/tests/atexit.rst
sage/doctest/tests/fail_and_die.rst
sage/doctest/tests/initial.rst
sage/doctest/tests/interrupt.rst
sage/doctest/tests/interrupt_diehard.rst
sage/doctest/tests/keyboardinterrupt.rst
sage/doctest/tests/longtime.rst
sage/doctest/tests/nodoctest
passagemath_repl-10.6.43.dist-info/METADATA
passagemath_repl-10.6.43.dist-info/WHEEL
passagemath_repl-10.6.43.dist-info/top_level.txt
passagemath_repl-10.6.43.dist-info/RECORD
