Metadata-Version: 2.4
Name: passagemath-repl
Version: 10.6.43
Summary: passagemath: IPython kernel, Sage preparser, doctester
Author-email: The Sage Developers <sage-support@googlegroups.com>
Maintainer: Matthias Köppe, passagemath contributors
License-Expression: GPL-2.0-or-later
Project-URL: release notes, https://github.com/passagemath/passagemath/releases
Project-URL: repo (upstream), https://github.com/sagemath/sage
Project-URL: repo, https://github.com/passagemath/passagemath
Project-URL: documentation, https://passagemath.org/docs/latest
Project-URL: homepage (upstream), https://www.sagemath.org
Project-URL: discourse, https://passagemath.discourse.group
Project-URL: tracker (upstream), https://github.com/sagemath/sage/issues
Project-URL: tracker, https://github.com/passagemath/passagemath/issues
Classifier: Development Status :: 6 - Mature
Classifier: Intended Audience :: Education
Classifier: Intended Audience :: Science/Research
Classifier: Operating System :: POSIX
Classifier: Operating System :: POSIX :: Linux
Classifier: Operating System :: MacOS :: MacOS X
Classifier: Operating System :: Microsoft :: Windows
Classifier: Programming Language :: Python :: 3 :: Only
Classifier: Programming Language :: Python :: 3.10
Classifier: Programming Language :: Python :: 3.11
Classifier: Programming Language :: Python :: 3.12
Classifier: Programming Language :: Python :: 3.13
Classifier: Programming Language :: Python :: 3.14
Classifier: Programming Language :: Python :: Implementation :: CPython
Classifier: Topic :: Scientific/Engineering :: Mathematics
Requires-Python: <3.15,>=3.10
Requires-Dist: passagemath-objects~=10.6.43.0
Requires-Dist: passagemath-environment~=10.6.43.0
Requires-Dist: ipykernel>=5.2.1
Requires-Dist: ipython>=7.13.0
Requires-Dist: ipywidgets>=7.5.1
Requires-Dist: jupyter-client
Requires-Dist: typing_extensions>=4.7.0; python_version < "3.13"
Provides-Extra: jupyterlab
Requires-Dist: jupyterlab; extra == "jupyterlab"
Provides-Extra: marimo
Requires-Dist: marimo; extra == "marimo"
Provides-Extra: notebook
Requires-Dist: notebook>=6.1.1; extra == "notebook"
Provides-Extra: sphinx
Requires-Dist: sphinx<9,>=5.2; extra == "sphinx"
